{"cameraMode":{"drawMode":0,"name":"Shaded","section":"Shading Mode"},"sceneLighting":false,"audioPlay":false,"sceneViewState":{"m_AlwaysRefresh":false,"showFog":true,"showSkybox":false,"showFlares":true,"showImageEffects":true,"showParticleSystems":true,"showVisualEffectGraphs":true,"m_FxEnabled":true},"in2DMode":false,"pivot":{"x":-0.001309964805841446,"y":-0.012544713914394379,"z":0.026522010564804078},"rotation":{"x":-0.17601923644542695,"y":0.025713127106428148,"z":-0.004593538586050272,"w":-0.9840515851974487},"size":0.13404899835586549,"orthographic":false}